smartchg/__init__.py
smartchg/__main__.py
smartchg/cli.py
smartchg-1.0.0.dist-info/LICENSE
smartchg-1.0.0.dist-info/METADATA
smartchg-1.0.0.dist-info/WHEEL
smartchg-1.0.0.dist-info/entry_points.txt
smartchg-1.0.0.dist-info/top_level.txt
smartchg-1.0.0.dist-info/RECORD
