Metadata-Version: 2.1
Name: smartchg
Version: 1.0.0
Summary: DCA-based asset exchange algorithm
Home-page: https://github.com/dmotte/smartchg
Author: dmotte
License: MIT
Keywords: calculator csv command value yield average return invest apy smartchg algorithm exchange change smart dca asset averaging
Classifier: Intended Audience :: End Users/Desktop
Classifier: Environment :: Console
Classifier: Natural Language :: English
Classifier: License :: OSI Approved :: MIT License
Classifier: Programming Language :: Python
Classifier: Programming Language :: Python :: 3
Classifier: Programming Language :: Python :: 3 :: Only
Classifier: Programming Language :: Python :: 3.10
Classifier: Topic :: Terminals
Classifier: Topic :: Utilities
Requires-Python: >=3.10.12
License-File: LICENSE
